{
  "DIA_BeatenCitizen_HELLO_03_01": "Спасибо за помощь!",
  "DIA_BeatenCitizen_HELLO_03_02": "Если бы не ты, меня бы уже не было.",
  "DIA_BeatenCitizen_HELLO_03_03": "Я не богат, но хочу, чтобы ты взял это золото в качестве благодарности.",
  "DIA_BeatenCitizen_Egoist_03_01": "Ещё раз спасибо за помощь!",
  "DIA_BeatenCitizen_Altruist_15_01": "Оставь себе это золото.",
  "DIA_BeatenCitizen_Altruist_03_02": "Ты меня удивил.",
  "DIA_BeatenCitizen_Altruist_03_05": "Ещё раз спасибо за помощь!",
  "DIA_BeatenCitizen_AfterEvent_03_01": "Береги себя!"
}
