{
  "DIA_ROLF_EXIT_15_01": "Stay close to me.",
  "DIA_ROLF_EXIT_03_02": "P-p-please, let's hurry! I can't stay he-here any longer!",
  "DIA_ROLF_EXIT_15_02": "Wait, wait, what about the gold?",
  "DIA_ROLF_EXIT_03_03": "Yeah, r-right. H-here, that's all I have.",
  "DIA_Rolf_SQ109_Hello_03_03": "May I-Innos reward you with children! I thought I was d-done f-f-for!",
  "DIA_Rolf_SQ109_Hello_15_04": "You have nothing to fear anymore.",
  "DIA_Rolf_SQ109_Hello_03_05": "F-for s-s-sure?!",
  "DIA_Rolf_SQ109_Hello_15_06": "I'm sure.",
  "DIA_Rolf_SQ109_Hello_HowLong_15_01": "How long have you been here?",
  "DIA_Rolf_SQ109_Hello_HowLong_03_02": "Whole a-ages, but fortunately for me wo-wo-wolves don't jump that high.",
  "DIA_Rolf_SQ109_Hello_GiveMeGold_15_01": "I don't plan on having children for now, but a purse would come in handy.",
  "DIA_Rolf_SQ109_Hello_GiveMeGold_03_02": "Y-yes... of course. M-my whole paycheck. As soon as I'm down, y-you'll get it.",
  "DIA_Rolf_SQ109_Hello_GoWithMe_15_04": "What happened?",
  "DIA_Rolf_SQ109_Hello_GoWithMe_03_05": "I was about to g-go back when I heard the wolves howling and so I ended up here, on-on this rock!",
  "DIA_Rolf_SQ109_Hello_GoWithMe_15_06": "Can you run?",
  "DIA_Rolf_SQ109_Hello_GoWithMe_03_07": "I'll manage somehow, just p-please get me home from h-here before that Beast shows up again!",
  "DIA_Rolf_SQ109_LetsGo_03_01": "G-good. I-I'm ready. Let's ge-get out of h-here!",
  "DIA_Rolf_SQ109_Beast_15_01": "You mentioned the Beast. What did it look like?",
  "DIA_Rolf_SQ109_Beast_03_02": "It was t-terrible! I've never seen anything like it! It was there, oh! By the trees ac-c-c-cross!",
  "DIA_Rolf_SQ109_FolkardMission_15_01": "Folkard sent me. He said you went to get some supplies.",
  "DIA_Rolf_SQ109_FolkardMission_03_02": "Most of them had been w-washed out by the water and had probably reached the sea by now, b-but there should have been a bottle of wine and some fish on the bo-bo-boat.",
  "DIA_Rolf_SQ109_FolkardMission_03_03": "Just don't make me go for it, because I'm not going!",
  "DIA_Rolf_SQ109_FolkardMission_03_04": "I've had enough adventures for t-today!",
  "DIA_Rolf_SQ109_Home_03_01": "Tha-Thank you! I o-o-owe you one!",
  "DIA_Rolf_SQ109_Hello_GiveMeGold_Choice": "I would have preferred a purse instead of children."
}