{
  "DIA_Tohar_QM202_Job_15_01": "Com'è il lavoro?",
  "DIA_Tohar_QM202_Job_03_02": "Lavoro? Quale lavoro?",
  "DIA_Tohar_QM202_Job_15_03": "L'ho chiesto perché ho qualcosa di veramente interessante da offrire. Probabilmente più interessante di quello che fai tu.",
  "DIA_Tohar_QM202_Job_03_04": "Chi ha detto che stavo facendo qualcosa? Ti sembro una specie di lavoratore? Ed è anche normale lavorare alla mia età?",
  "DIA_Tohar_QM202_Job_15_05": "Beh, probabilmente non sei più giovane di me.",
  "DIA_Tohar_QM202_Job_03_06": "Forse, ma la vita non è ancora così incasinata che debba andare a lavorare.",
  "DIA_Tohar_QM202_Help_15_01": "Non vorresti alleviare il peso dei tuoi genitori?",
  "DIA_Tohar_QM202_Help_03_02": "Chi dice che hanno troppo da fare? Stanno bene, non hanno bisogno del mio supporto.",
  "DIA_Tohar_QM202_Help_15_03": "Ma se portassi qualcosa a casa, sono sicuro che te ne sarebbero grati...",
  "DIA_Tohar_QM202_Help_03_04": "Senti, qual è il tuo problema? Sei venuto qui apposta per infastidirmi? Risparmiatelo, è un passatempo stupido!",
  "DIA_Tohar_QM202_Help_15_05": "No, sono venuto...",
  "DIA_Tohar_QM202_Help_03_06": "Non mi interessa! Arrivederci.",
  "DIA_Tohar_YouSure_09_01": "Già."
}