{
  "DIA_Fabio_Q101_AfterFight_05_01": "Mein Kopf ... was willst du noch, du Schei... äh ... Kleiner?",
  "DIA_Fabio_Q101_AfterFight_05_02": "Suchst du immer noch Ärger, du kleiner Rotzlöffel?",
  "DIA_Fabio_Q101_Hello_15_01": "Du siehst von der Reise nicht mitgenommen aus.",
  "DIA_Fabio_Q101_Hello_05_02": "Willst du dir eine fangen?",
  "DIA_Fabio_Q101_Hello1_15_01": "Ganz ruhig, ich habe ja nur gefragt. Ich gehe dann mal wieder.",
  "DIA_Fabio_Q101_Hello1_05_02": "So ist es richtig. Ich habe akuten Biermangel, daher bin so schlecht gelaunt und brauche keinen Rotzbengel wie dich, der mir das Ohr abkaut.",
  "DIA_Fabio_Q101_Hello1_05_03": "Kannst du dir das vorstellen? Diese Armleuchter da oben haben mir nicht einen Schluck Alkohol während der gesamten Fahrt gegeben!",
  "DIA_Fabio_Q101_Hello1_15_04": "Mir auch nicht.",
  "DIA_Fabio_Q101_Hello1_05_05": "Wenn ich mir dich Weichei ansehe, kein Wunder!",
  "DIA_Fabio_Q101_Hello2_15_01": "Jemand sollte dir mal eine Lektion in Sachen Manieren erteilen.",
  "DIA_Fabio_Q101_Hello2_05_02": "Und dieser jemand ist ein Schwächling wie du?",
  "DIA_Fabio_Q101_Hello2_15_03": "Hast du ein Problem?",
  "DIA_Fabio_Q101_Hello2_05_04": "Ich? Überhaupt nicht, aber dein geschwätziges Gesicht ist dabei, eins zu bekommen!",
  "DIA_Fabio_Q101_Beer_15_01": "Ich habe dir ein Bier mitgebracht.",
  "DIA_Fabio_Q101_Beer_05_02": "Ah ... genau was ich gebraucht habe ...",
  "DIA_Fabio_Q101_Beer_15_03": "Besser?",
  "DIA_Fabio_Q101_Beer_05_04": "Zisch ab, oder ich hau dir auf's Maul!",
  "DIA_Fabio_Q101_Beer_15_05": "Damit hätte ich rechnen können ..."
}