{
  "DIA_ArmorSeller_Hello_15_01": "Ki vagy te?",
  "DIA_ArmorSeller_Hello_03_02": "Páncélkészítő vagyok, és ez a szerény kis műhelyem.",
  "DIA_ArmorSeller_Hello_03_03": "Ha bárkit látsz a városban olyan ruhában amin egy kicsi védelem is van, az biztosan volt a két kezem között.",
  "DIA_ArmorSeller_Hello_03_04": "Mondd csak, miben segíthetek? Páncélzatokat árulok, de fejlesztést is vállalok.",
  "DIA_ArmorSeller_Upgrade_15_01": "Páncélzat fejlesztést?",
  "DIA_ArmorSeller_Upgrade_03_02": "A páncélok zömét úgy alakították ki, hogy mindenkinek megfeleljen.",
  "DIA_ArmorSeller_Upgrade_03_03": "Minden elemét gondosan illesztek be, és ahol szükséges, megerősítem azt.",
  "DIA_ArmorSeller_Upgrade_03_04": "Így nem csak kényelmesebben lehet bennük mozogni, de több védelmet is nyújt. Persze ez azért nem megvalósítható minden páncéllal.",
  "DIA_ArmorSeller_Upgrade_03_05": "Csak mutasd meg, hogy mid van én meg megmondom mit tehetek, mik szükségesek és mennyibe fog kerülni.",
  "DIA_ArmorSeller_Teach_03_02": "Azt kockáztassam, hogy tönkreteszed az üzletemet? Nem adom tovább a tudásomat, és nem is keresek tanoncot."
}