{
  "DIA_Smith_NS56_Start_03_01": "Hey! Hast nicht vielleicht zwei Rohstahl bei dir?",
  "DIA_Smith_NS56_NoItmiswordraw_15_01": "Wie viel Stahl brauchst du?",
  "DIA_Smith_NS56_NoItmiswordraw_03_02": "Zwei, Das genügt.",
  "DIA_Smith_NS56_Itmiswordraw_15_01": "Hier ist der Stahl.",
  "DIA_Smith_NS56_Itmiswordraw_03_02": "Vielen Dank! Komm später wieder, dann bekommst du etwas für deine Hilfe!",
  "DIA_Smith_NS56_Reward_03_01": "Ich bin leider noch nicht fertig.",
  "DIA_Smith_NS56_Reward_03_02": "Hier, das ist für dich! Möge es dir gute Dienste leisten!",
  "DIA_Smith_NS56_AfterAfter_03_01": "Tut mir leid, ich habe es eilig."
}
