{
  "DIA_Broddy_EXIT_15_01": "W zasadzie, to muszę już iść.",
  "DIA_Broddy_EXIT_03_02": "Słuszna decyzja.",
  "DIA_Broddy_AmbientBeforeJoin_03_01": "Co się gapisz, gnojku?",
  "DIA_Broddy_AmbientBeforeJoin_03_02": "Mam cię na oku, smarkaczu.",
  "DIA_Broddy_Q205_AllDay_15_01": "Cały dzień tak tutaj siedzisz?",
  "DIA_Broddy_Q205_AllDay_03_02": "Tak.",
  "DIA_Broddy_Q205_Move_15_01": "Nigdzie się nie ruszasz?",
  "DIA_Broddy_Q205_Move_03_02": "Nie.",
  "DIA_Broddy_Q205_Salvi_15_01": "Nawet jeśli Salvi ci rozkaże?",
  "DIA_Broddy_Q205_Salvi_03_02": "Wtedy to co innego...",
  "DIA_Broddy_Q205_Salvi_03_03": "Zresztą, zejdź mi z oczu i pozwól spokojnie zjeść ten paskudny czerstwy chleb.",
  "DIA_Broddy_Q205_Hungry_15_01": "Wydawało mi się, że macie całkiem sporo zapasów.",
  "DIA_Broddy_Q205_Hungry_03_02": "W tym rzecz! Mamy tego kilka skrzynek, ale Salvi zabrania mi się porządnie najeść bo według niego obżeram się jak kretoszczur.",
  "DIA_Broddy_Q205_Hungry_03_03": "Według niego jeszcze trochę, a nawet walczyć nie będę mógł. Co on tam może wiedzieć!",
  "DIA_Broddy_Q205_Hungry_03_04": "Jak byliśmy w koszarach to jedzenie było paskudne, jak mamy dobre jedzenie to nie pozwala mi sobie podjeść!",
  "DIA_Broddy_Q205_Smell_03_01": "Czujesz to? Czy ktoś gotował gulasz?",
  "DIA_Broddy_Q205_Smell_15_02": "Tak, właśnie ugotowaliśmy go w grocie ze skrzyniami.",
  "DIA_Broddy_Q205_Smell_15_03": "Masz, spróbuj.",
  "DIA_Broddy_Q205_Smell_15_04": "Jeśli się pośpieszysz, to może jeszcze coś dla ciebie zostanie.",
  "DIA_Broddy_Q205_Smell_03_05": "Cholera, nie wytrzymam tu dłużej, MUSZĘ zjeść coś porządnego!",
  "DIA_Broddy_QM401_Fight_03_01": "Proszę, proszę, kogo my tu mamy?",
  "DIA_Broddy_QM401_Fight_03_02": "Berto, ty zdrajco, zaniosę twoją głowę Salviemu!",
  "DIA_Broddy_QM401_Fight_Traitor_15_01": "Czy ktoś kto zdradza zdrajców jest zdrajcą?",
  "DIA_Broddy_QM401_Fight_Traitor_03_02": "O czym ty do mnie mówisz? Do cholery z wami!"
}