{
  "DIA_Riordian_SQ121_Cutscene_03_01": "Lass uns warten, bis Lokvar eingeschlafen ist. Bis dahin werde ich dir die Grundlagen beibringen, wie man Spruchrollen abschreibt. Hier, mein Handbuch.",
  "DIA_Riordian_SQ121_Cutscene_03_02": "... nochmal zusammengefasst: Um eine neue Spruchrolle abzuschreiben, brauchst du ein leeres Pergament und eine fertige Spruchrolle desselben Zaubers.",
  "DIA_Riordian_SQ121_Cutscene_03_03": "Je nachdem wie mächtig der Zauber ist, brauchst du entweder magisches Erzpulver oder reine Erzbrocken.",
  "DIA_Riordian_SQ121_Cutscene_03_04": "Dann setzt du dich ans Schreibpult und zeichnest mit diesem Erz alles ab.",
  "DIA_Riordian_SQ121_Cutscene_03_05": "Los gehts, Lokvar schläft wahrscheinlich schon.",
  "DIA_Riordian_SQ121_Cutscene_03_06": "Benutze diesen Zauber um sicherzugehen, aber komm nicht zu nah. Er könnte dich hören."
}