{
  "DIA_Kazeem_Q101_WhatsUp_15_00": "Jak podróż?",
  "DIA_Kazeem_Q101_WhatsUp_12_01": "Mam nadzieję, że niedługo dobijemy do brzegu.",
  "DIA_Kazeem_Q101_WhatsUp_12_02": "Jeszcze tak trochę potrzęsie, a zwrócę cały obiad!",
  "DIA_Kazeem_Q101_Hello_15_00": "Nie jesteś stąd, prawda?",
  "DIA_Kazeem_Q101_Hello_12_01": "Przybywam z Wysp Południowych.",
  "DIA_Kazeem_Q101_Hello_15_02": "To kawał stąd. Czego szukasz na Archolos?",
  "DIA_Kazeem_Q101_Hello_12_03": "To, co robię, to moja prywatna sprawa.",
  "DIA_Kazeem_Q101_Hello_12_04": "Nie mam w zwyczaju żalić się obcym, dlatego wolałbym, żeby tak pozostało.",
  "DIA_Kazeem_Q101_Ambient_12_01": "Zostaw mnie w spokoju."
}