{
  "DIA_AppleTrader_ApplesAlmostFree_03_01": "Jabłka! Świeże jabłka! Za półdarmo!",
  "DIA_AppleTrader_WhyFree_15_01": "Za półdarmo?",
  "DIA_AppleTrader_WhyFree_03_02": "Cóż przywiozłem kilka skrzyń jabłek do miasta.",
  "DIA_AppleTrader_WhyFree_03_03": "Wszystkie miały zostać załadowane na jeden ze statków.",
  "DIA_AppleTrader_WhyFree_03_04": "Niestety nie dogadałem się z załogą i część skrzyń została w porcie.",
  "DIA_AppleTrader_WhyFree_03_05": "Nie opłaca mi się targać tego z powrotem do domu więc zostaje w mieście na jakiś czas.",
  "DIA_AppleTrader_WhyFree_03_06": "To jak chłopcze skusisz się?",
  "DIA_AppleTrader_WhyFree_03_07": "Cztery sztuki złota za soczyste jabłko!",
  "DIA_AppleTrader_BuyApple_Description": "Poproszę jabłko. (4 SZ)",
  "DIA_AppleTrader_BuyApple_15_01": "Poproszę jabłko.",
  "DIA_AppleTrader_BuyApple_03_02": "Powiedziałem za półdarmo a nie za darmo!",
  "DIA_AppleTrader_BuyApple_03_03": "Wróć jak zdobędziesz złoto!",
  "DIA_AppleTrader_BuyApple_03_04": "Proszę bardzo!",
  "DIA_AppleTrader_BuyApple_03_05": "Wybacz, nie mam więcej przy sobie! Wróć później!",
  "DIA_AppleTrader_BuyApple_03_06": "Wybacz, sprzedałem już wszystkie jabłka!",
  "DIA_AppleTrader_BuyApple_03_07": "Ale dziękuję za zainteresowanie!"
}
