{
  "DIA_Broddy_EXIT_15_01": "Valójában most nekem mennem kell.",
  "DIA_Broddy_EXIT_03_02": "Ez a jó döntés.",
  "DIA_Broddy_AmbientBeforeJoin_03_01": "Mit nézel, taknyos?",
  "DIA_Broddy_AmbientBeforeJoin_03_02": "Szemmel tartalak, te kis köcsög.",
  "DIA_Broddy_Q205_AllDay_15_01": "Egész nap csak itt üldögélsz?",
  "DIA_Broddy_Q205_AllDay_03_02": "Ja.",
  "DIA_Broddy_Q205_Move_15_01": "Nem mész semerre sem?",
  "DIA_Broddy_Q205_Move_03_02": "Nem.",
  "DIA_Broddy_Q205_Salvi_15_01": "Még akkor sem, ha Salvi parancsolja?",
  "DIA_Broddy_Q205_Salvi_03_02": "Az más...",
  "DIA_Broddy_Q205_Salvi_03_03": "Mindegy, tűnj a szemem elől és hagyd nyugodtan ennem ezt az undorító és áporodott kenyeret.",
  "DIA_Broddy_Q205_Hungry_15_01": "Azt hittem kaptál elég ellátmányt.",
  "DIA_Broddy_Q205_Hungry_03_02": "A helyzet a következő! Több ládánk is van de Salvi megtiltotta, hogy rendesen étkezzek, mert azt hiszi, úgy falok mint egy vakondpatkány.",
  "DIA_Broddy_Q205_Hungry_03_03": "Azt mondta, ha többet eszem, nem tudok majd rendesen harcolni. Ennek a fickónak fingja sincs!",
  "DIA_Broddy_Q205_Hungry_03_04": "A kaszárnyában borzalmas volt a kaja, itt pedig, ahol jókat ehetünk, nem kaphatok!",
  "DIA_Broddy_Q205_Smell_03_01": "Érzed ezt? Valaki pörköltet készített?",
  "DIA_Broddy_Q205_Smell_15_02": "Igen, most főztük meg a bányában a ládáknál.",
  "DIA_Broddy_Q205_Smell_15_03": "Tessék, kóstold meg.",
  "DIA_Broddy_Q205_Smell_15_04": "Ha sietsz, akkor még talán maradt neked is.",
  "DIA_Broddy_Q205_Smell_03_05": "Francba, már nem bírom itt ki tovább, MUSZÁJ ennem valami normálisat!",
  "DIA_Broddy_QM401_Fight_03_01": "Nos, nos, nos, kit látnak szemeim?",
  "DIA_Broddy_QM401_Fight_03_02": "Berto, te áruló, elviszem a fejedet Salvinak!",
  "DIA_Broddy_QM401_Fight_Traitor_15_01": "Áruló az, aki árulókat árul el?",
  "DIA_Broddy_QM401_Fight_Traitor_03_02": "Mit akarsz tőlem? A pokolba veled!"
}