{
  "DIA_Fabio_Q101_AfterFight_05_01": "Моя голова... чего ты ещё хочешь, гов... э-э-э... парень?",
  "DIA_Fabio_Q101_AfterFight_05_02": "Всё ещё ищешь неприятности, сопляк?",
  "DIA_Fabio_Q101_Hello_15_01": "Ты не выглядишь уставшим от этого путешествия.",
  "DIA_Fabio_Q101_Hello_05_02": "А в морду хочешь?",
  "DIA_Fabio_Q101_Hello1_15_01": "Спокойно, я просто спросил. Уже ухожу.",
  "DIA_Fabio_Q101_Hello1_05_02": "Ну и правильно. Я очень хочу пива, поэтому я такой нервный и не терплю таких сопляков, как ты.",
  "DIA_Fabio_Q101_Hello1_05_03": "Вообще, ты можешь себе представить? Эти гады сверху не дали мне ни капли выпивки за всё путешествие!",
  "DIA_Fabio_Q101_Hello1_15_04": "И мне тоже.",
  "DIA_Fabio_Q101_Hello1_05_05": "Глядя на такого слабака, как ты, я не удивляюсь!",
  "DIA_Fabio_Q101_Hello2_15_01": "Кажется, кто-то должен преподать тебе урок хороших манер.",
  "DIA_Fabio_Q101_Hello2_05_02": "И этот кто-то будет таким же хлюпиком, как ты?",
  "DIA_Fabio_Q101_Hello2_15_03": "У тебя какие-то проблемы?",
  "DIA_Fabio_Q101_Hello2_05_04": "У меня? Отнюдь, но у твоей болтливой морды скоро будут!",
  "DIA_Fabio_Q101_Beer_15_01": "Я принёс тебе пиво.",
  "DIA_Fabio_Q101_Beer_05_02": "Ах... то, что нужно...",
  "DIA_Fabio_Q101_Beer_15_03": "Лучше?",
  "DIA_Fabio_Q101_Beer_05_04": "Проваливай, а то я тебе врежу!",
  "DIA_Fabio_Q101_Beer_15_05": "Мне следовало ожидать этого..."
}