{
"DIA_Thamil_HELLO_03_01" : "Doufám, že záležitost, kterou pro mě máš, bude stát za to.",
"DIA_Thamil_HELLO_03_02" : "Jestli si chceš něco koupit, promluv si s Adrienem. Má na starosti prodej.",
"DIA_Thamil_House_15_01" : "Máš celkem pěkný dům.",
"DIA_Thamil_House_03_02" : "Ó, děkuji, děkuji.",
"DIA_Thamil_House_03_03" : "Ve skutečnosti je to moje zlatnická dílna, kterou jsem si pronajala od bývalého majitele - ať odpočívá v pokoji.",
"DIA_Thamil_House_03_04" : "Ten nakonec zemřel a já jsem najala učně a rozšířila ji na velikost celého cechu.",
"DIA_Thamil_Goldsmith_15_01" : "Jsi zlatnice?",
"DIA_Thamil_Goldsmith_03_02" : "Mistryně zlatnice, když už se ptáš, a jmenuji se Susanne.",
"DIA_Thamil_Goldsmith_15_03" : "Já Marvin.",
"DIA_Thamil_Goldsmith_03_04" : "Chceš něco?",
"DIA_Thamil_Have_15_01" : "Co máš na skladě?",
"DIA_Thamil_Have_03_02" : "O prodej se stará jeden z mých učňů, Adrien.",
"DIA_Thamil_Have_03_03" : "Přijímám jen speciální zakázky.",
"DIA_Thamil_Have_Special_03_04" : "Možná by sis chtěl prohlédnout mou nabídku? Jen nezapomeň, že dokončení každého z těchto předmětů obvykle trvá několik dní.",
"DIA_Thamil_Have_Special_15_05" : "Několik dní?",
"DIA_Thamil_Have_Special_03_06" : "Opravdové umění vyžaduje čas a já zde nabízím jen to nejlepší!",
"DIA_Thamil_Have_Special_15_01" : "Co myslíš speciálními zakázkami?",
"DIA_Thamil_Have_Special_03_02" : "Šperky dělané z kvalitní rudy a drahých kamenů.",
"DIA_Thamil_Have_Special_03_03" : "Vidím, že mám před sebou opravdu důstojného hosta!",
"DIA_Thamil_Have_Special_03_07" : "Ale nedělej si iluze - někdo jako ty si to rozhodně nemůže dovolit!",
"DIA_Thamil_Have_Special_15_08" : "Jak bys to mohla vědět?",
"DIA_Thamil_Have_Special_03_09" : "Bez urážky, ale stačí jeden pohled na tebe. Náhodou znám lidi jako málokdo jiný!",
"DIA_Thamil_CanTrade_03_01" : "Vidím, že se ti v poslední době daří, chlapče!",
"DIA_Thamil_TRADE_15_01" : "Ukaž mi svou speciální nabídku.",
"DIA_Thamil_TRADE_03_02" : "Tady to je.",
"DIA_Thamil_TRADE_03_03" : "Vyber si, co tě zajímá.",
"DIA_Thamil_TRADE_03_04" : "Figurky, prsteny, náhrdelníky pro tvou milou nebo třeba amulety?",
"DIA_Thamil_Ambient_03_04" : "Je pravda, když se říká, že zlato není všechno.",
"DIA_Thamil_Ambient_03_05" : "Je tu také stříbro a šperky, bez nichž by moje práce nebyla ničím.",
"DIA_Thamil_Have_Special_Choice" : "Speciální zakázky?"
}
